{
  "updated_at": "2026-07-11T06:05:19.605656+08:00",
  "topics": [
    {
      "title": "脆友圈圖表掀流行\n用戶流行分享脆友圈圖表，除感謝好友也好奇如何製作或用來查帳 · 61 萬 則貼文",
      "description": "脆友圈圖表掀流行\n用戶流行分享脆友圈圖表，除感謝好友也好奇如何製作或用來查帳",
      "count": "61 萬 則貼文",
      "link": "https://www.threads.com/search?q=%E8%84%86%E5%8F%8B%E5%9C%88&serp_type=trends&trend_fbid=1023949260011738"
    },
    {
      "title": "HAHABABY被指抄襲日牌\n二伯品牌設計疑抄SOU・SOU，日方關注四年後她開直播回應 · 74 萬 則貼文",
      "description": "HAHABABY被指抄襲日牌\n二伯品牌設計疑抄SOU・SOU，日方關注四年後她開直播回應",
      "count": "74 萬 則貼文",
      "link": "https://www.threads.com/search?q=HAHABABY&serp_type=trends&trend_fbid=3071569983045667"
    },
    {
      "title": "明宰鉉錄音檔助粉絲自保\n男團成員明宰鉉錄製「出獄復仇」語音，供粉絲深夜搭計程車時用於自保 · 8 千 則貼文",
      "description": "明宰鉉錄音檔助粉絲自保\n男團成員明宰鉉錄製「出獄復仇」語音，供粉絲深夜搭計程車時用於自保",
      "count": "8 千 則貼文",
      "link": "https://www.threads.com/search?q=%E6%98%8E%E5%AE%B0%E9%89%89&serp_type=trends&trend_fbid=1069640518836148"
    },
    {
      "title": "台南停班停課\n受巴威颱風影響，台南沿海最大陣風達10級，部分地區已停電 · 6 萬 則貼文",
      "description": "台南停班停課\n受巴威颱風影響，台南沿海最大陣風達10級，部分地區已停電",
      "count": "6 萬 則貼文",
      "link": "https://www.threads.com/search?q=%E5%8F%B0%E5%8D%97&serp_type=trends&trend_fbid=1600185128342831"
    },
    {
      "title": "巴威颱風襲台多地停班課\n巴威颱風挾強風豪雨襲台造成部分地區停電與廣告牌倒塌 · 53 萬 則貼文",
      "description": "巴威颱風襲台多地停班課\n巴威颱風挾強風豪雨襲台造成部分地區停電與廣告牌倒塌",
      "count": "53 萬 則貼文",
      "link": "https://www.threads.com/search?q=%E5%B7%B4%E5%A8%81%E9%A2%B1%E9%A2%A8&serp_type=trends&trend_fbid=1641132240320298"
    }
  ]
}