{
  "updated_at": "2026-05-20T08:05:27.908849+08:00",
  "topics": [
    {
      "title": "2026國際布克獎得主揭曉\n2026年國際布克獎於倫敦公布得主，為全球翻譯小說界最高榮譽之一 · 17 萬 則貼文",
      "description": "2026國際布克獎得主揭曉\n2026年國際布克獎於倫敦公布得主，為全球翻譯小說界最高榮譽之一",
      "count": "17 萬 則貼文",
      "link": "https://www.threads.com/search?q=%E5%B8%83%E5%85%8B%E7%8D%8E&serp_type=trends&trend_fbid=975733381843966"
    },
    {
      "title": "520爆出軌控訴潮\n適逢520網路情人節，許多人揭露伴侶不忠，並公布其任職於科技業或海底撈等資訊 · 1 萬 則貼文",
      "description": "520爆出軌控訴潮\n適逢520網路情人節，許多人揭露伴侶不忠，並公布其任職於科技業或海底撈等資訊",
      "count": "1 萬 則貼文",
      "link": "https://www.threads.com/search?q=%E5%87%BA%E8%BB%8C&serp_type=trends&trend_fbid=1302068484714349"
    },
    {
      "title": "北科大碩士生離世\n北科大電機所研究生逝世，友人指稱其不堪指導教授學術壓力，每日需在實驗室工作12小時 · 26 萬 則貼文",
      "description": "北科大碩士生離世\n北科大電機所研究生逝世，友人指稱其不堪指導教授學術壓力，每日需在實驗室工作12小時",
      "count": "26 萬 則貼文",
      "link": "https://www.threads.com/search?q=%E5%8C%97%E7%A7%91%E5%A4%A7&serp_type=trends&trend_fbid=4497497137201828"
    },
    {
      "title": "520情侶放閃、單身自嘲\n520網路情人節情侶慶祝、單身族幽默應對，手搖飲品牌「得正」也搶搭商機 · 18 萬 則貼文",
      "description": "520情侶放閃、單身自嘲\n520網路情人節情侶慶祝、單身族幽默應對，手搖飲品牌「得正」也搶搭商機",
      "count": "18 萬 則貼文",
      "link": "https://www.threads.com/search?q=520&serp_type=trends&trend_fbid=1380528407292261"
    },
    {
      "title": "湯令山新歌《玻璃》上架\n湯令山新歌《玻璃》錄音室版，選在520正式發行 · 2 萬 則貼文",
      "description": "湯令山新歌《玻璃》上架\n湯令山新歌《玻璃》錄音室版，選在520正式發行",
      "count": "2 萬 則貼文",
      "link": "https://www.threads.com/search?q=%E7%8E%BB%E7%92%83&serp_type=trends&trend_fbid=1548289333690398"
    }
  ]
}